mld/Interface.py
mld/InterfaceMLD.py
mld/__init__.py
mld/utils.py
mld/mld1/GroupState.py
mld/mld1/RouterState.py
mld/mld1/__init__.py
mld/mld1/mld_globals.py
mld/mld1/nonquerier/CheckingListeners.py
mld/mld1/nonquerier/ListenersPresent.py
mld/mld1/nonquerier/NoListenersPresent.py
mld/mld1/nonquerier/NonQuerier.py
mld/mld1/nonquerier/__init__.py
mld/mld1/querier/CheckingListeners.py
mld/mld1/querier/ListenersPresent.py
mld/mld1/querier/NoListenersPresent.py
mld/mld1/querier/Querier.py
mld/mld1/querier/__init__.py
mld/mld1/wrapper/CheckingListeners.py
mld/mld1/wrapper/ListenersPresent.py
mld/mld1/wrapper/NoListenersPresent.py
mld/mld1/wrapper/__init__.py
mld/packet/Packet.py
mld/packet/PacketIpHeader.py
mld/packet/PacketMLDHeader.py
mld/packet/PacketPayload.py
mld/packet/ReceivedPacket.py
mld/packet/__init__.py
mld/rwlock/RWLock.py
mld/rwlock/__init__.py
py_mld-1.0.3.dist-info/LICENSE
py_mld-1.0.3.dist-info/METADATA
py_mld-1.0.3.dist-info/WHEEL
py_mld-1.0.3.dist-info/top_level.txt
py_mld-1.0.3.dist-info/RECORD
