Metadata-Version: 2.1
Name: py-mld
Version: 1.0.3
Summary: MLDv1 router-side protocol implementation for Python
Home-page: http://github.com/pedrofran12/mld
Author: Pedro Oliveira
Author-email: pedro.francisco.oliveira@tecnico.ulisboa.pt
License: MIT
Keywords: MLD MLDv1 Router IPv6 Multicast Interest
Platform: any
Classifier: Development Status :: 4 - Beta
Classifier: Environment :: Console
Classifier: Intended Audience :: Information Technology
Classifier: Topic :: System :: Networking
Classifier: License :: OSI Approved :: MIT License
Classifier: Natural Language :: English
Classifier: Operating System :: OS Independent
Classifier: Programming Language :: Python
Classifier: Programming Language :: Python :: 3
Classifier: Programming Language :: Python :: 3.3
Classifier: Programming Language :: Python :: 3.4
Classifier: Programming Language :: Python :: 3.5
Classifier: Programming Language :: Python :: 3.6
Classifier: Programming Language :: Python :: 3.7
Classifier: Programming Language :: Python :: 3.8
Classifier: Programming Language :: Python :: 3.9
Requires-Python: >=3.3
License-File: LICENSE
Requires-Dist: netifaces
Requires-Dist: ipaddress
